[
  { "word": "sein", "en_meaning": "to be" },
  { "word": "haben", "en_meaning": "to have" },
  { "word": "werden", "en_meaning": "to become" },
  { "word": "können", "en_meaning": "can" },
  { "word": "müssen", "en_meaning": "must" },
  { "word": "sollen", "en_meaning": "should" },
  { "word": "wollen", "en_meaning": "want" },
  { "word": "dürfen", "en_meaning": "may" },
  { "word": "machen", "en_meaning": "to make/do" },
  { "word": "gehen", "en_meaning": "to go" },
  { "word": "kommen", "en_meaning": "to come" },
  { "word": "sehen", "en_meaning": "to see" },
  { "word": "essen", "en_meaning": "to eat" },
  { "word": "trinken", "en_meaning": "to drink" },
  { "word": "schlafen", "en_meaning": "to sleep" },
  { "word": "arbeiten", "en_meaning": "to work" },
  { "word": "lesen", "en_meaning": "to read" },
  { "word": "schreiben", "en_meaning": "to write" },
  { "word": "sprechen", "en_meaning": "to speak" },
  { "word": "hören", "en_meaning": "to hear" },
  { "word": "fahren", "en_meaning": "to drive/go" },
  { "word": "laufen", "en_meaning": "to run" },
  { "word": "stehen", "en_meaning": "to stand" },
  { "word": "sitzen", "en_meaning": "to sit" },
  { "word": "bleiben", "en_meaning": "to stay" },
  { "word": "lernen", "en_meaning": "to learn" },
  { "word": "vergessen", "en_meaning": "to forget" },
  { "word": "erinnern", "en_meaning": "to remember" },
  { "word": "fragen", "en_meaning": "to ask" },
  { "word": "antworten", "en_meaning": "to answer" },
  { "word": "kaufen", "en_meaning": "to buy" },
  { "word": "verkaufen", "en_meaning": "to sell" },
  { "word": "beginnen", "en_meaning": "to begin" },
  { "word": "enden", "en_meaning": "to end" },
  { "word": "finden", "en_meaning": "to find" },
  { "word": "verlieren", "en_meaning": "to lose" },
  { "word": "zeigen", "en_meaning": "to show" },
  { "word": "bringen", "en_meaning": "to bring" },
  { "word": "nehmen", "en_meaning": "to take" },
  { "word": "geben", "en_meaning": "to give" },
  { "word": "denken", "en_meaning": "to think" },
  { "word": "glauben", "en_meaning": "to believe" },
  { "word": "wissen", "en_meaning": "to know" },
  { "word": "verstehen", "en_meaning": "to understand" },
  { "word": "spielen", "en_meaning": "to play" },
  { "word": "leben", "en_meaning": "to live" },
  { "word": "sterben", "en_meaning": "to die" },
  { "word": "suchen", "en_meaning": "to search" },
  { "word": "erklären", "en_meaning": "to explain" },
  { "word": "benutzen", "en_meaning": "to use" },
  { "word": "probieren", "en_meaning": "to try" },
  { "word": "beenden", "en_meaning": "to finish" },
  { "word": "fortsetzen", "en_meaning": "to continue" },
  { "word": "verändern", "en_meaning": "to change" },
  { "word": "reisen", "en_meaning": "to travel" },
  { "word": "singen", "en_meaning": "to sing" },
  { "word": "tanzen", "en_meaning": "to dance" },
  { "word": "bieten", "en_meaning": "to offer" },
  { "word": "erhalten", "en_meaning": "to receive" },
  { "word": "erzählen", "en_meaning": "to tell" },
  { "word": "verbinden", "en_meaning": "to connect" },
  { "word": "entdecken", "en_meaning": "to discover" },
  { "word": "erlauben", "en_meaning": "to allow" },
  { "word": "verweigern", "en_meaning": "to refuse" },
  { "word": "versuchen", "en_meaning": "to attempt" },
  { "word": "öffnen", "en_meaning": "to open" },
  { "word": "schließen", "en_meaning": "to close" },
  { "word": "kochen", "en_meaning": "to cook" },
  { "word": "backen", "en_meaning": "to bake" },
  { "word": "putzen", "en_meaning": "to clean" },
  { "word": "waschen", "en_meaning": "to wash" },
  { "word": "schneiden", "en_meaning": "to cut" },
  { "word": "messen", "en_meaning": "to measure" },
  { "word": "warten", "en_meaning": "to wait" },
  { "word": "tragen", "en_meaning": "to carry" },
  { "word": "ziehen", "en_meaning": "to pull" },
  { "word": "drücken", "en_meaning": "to push" },
  { "word": "fühlen", "en_meaning": "to feel" },
  { "word": "lauschen", "en_meaning": "to listen" },
  { "word": "schauen", "en_meaning": "to look" },
  { "word": "drehen", "en_meaning": "to turn" },
  { "word": "fliegen", "en_meaning": "to fly" },
  { "word": "übernachten", "en_meaning": "to stay overnight" },
  { "word": "erleben", "en_meaning": "to experience" },
  { "word": "beachten", "en_meaning": "to notice" },
  { "word": "überlegen", "en_meaning": "to consider" },
  { "word": "vergleichen", "en_meaning": "to compare" },
  { "word": "zählen", "en_meaning": "to count" },
  { "word": "rechnen", "en_meaning": "to calculate" },
  { "word": "informieren", "en_meaning": "to inform" },
  { "word": "forschen", "en_meaning": "to research" },
  { "word": "entwickeln", "en_meaning": "to develop" },
  { "word": "verbessern", "en_meaning": "to improve" },
  { "word": "veröffentlichen", "en_meaning": "to publish" },
  { "word": "bearbeiten", "en_meaning": "to edit" },
  { "word": "umsetzen", "en_meaning": "to implement" },
  { "word": "anpassen", "en_meaning": "to adjust" },
  { "word": "überprüfen", "en_meaning": "to check" },
  { "word": "sichern", "en_meaning": "to secure" },
  { "word": "analysieren", "en_meaning": "to analyze" },
  { "word": "kooperieren", "en_meaning": "to cooperate" },
  { "word": "verhandeln", "en_meaning": "to negotiate" },
  { "word": "organisieren", "en_meaning": "to organize" },
  { "word": "planen", "en_meaning": "to plan" },
  { "word": "entwerfen", "en_meaning": "to design" },
  { "word": "gestalten", "en_meaning": "to shape" },
  { "word": "kontrollieren", "en_meaning": "to control" },
  { "word": "verwalten", "en_meaning": "to manage" },
  { "word": "prüfen", "en_meaning": "to examine" },
  { "word": "pflegen", "en_meaning": "to maintain" },
  { "word": "reparieren", "en_meaning": "to repair" },
  { "word": "korrigieren", "en_meaning": "to correct" },
  { "word": "einschätzen", "en_meaning": "to assess" },
  { "word": "erforschen", "en_meaning": "to explore" },
  { "word": "bereitstellen", "en_meaning": "to provide" },
  { "word": "verleihen", "en_meaning": "to award" },
  { "word": "feiern", "en_meaning": "to celebrate" },
  { "word": "unterstützen", "en_meaning": "to support" },
  { "word": "auswählen", "en_meaning": "to choose" },
  { "word": "beweisen", "en_meaning": "to prove" },
  { "word": "empfehlen", "en_meaning": "to recommend" },
  { "word": "vorschlagen", "en_meaning": "to suggest" },
  { "word": "akzeptieren", "en_meaning": "to accept" },
  { "word": "ablehnen", "en_meaning": "to reject" },
  { "word": "überzeugen", "en_meaning": "to convince" },
  { "word": "ermutigen", "en_meaning": "to encourage" },
  { "word": "anbieten", "en_meaning": "to offer" },
  { "word": "akquirieren", "en_meaning": "to acquire" },
  { "word": "initieren", "en_meaning": "to initiate" },
  { "word": "koordinieren", "en_meaning": "to coordinate" },
  { "word": "evaluieren", "en_meaning": "to evaluate" },
  { "word": "entwickeln", "en_meaning": "to create" },
  { "word": "schützen", "en_meaning": "to protect" },
  { "word": "erhalten", "en_meaning": "to obtain" },
  { "word": "ausführen", "en_meaning": "to execute" },
  { "word": "vermitteln", "en_meaning": "to mediate" },
  { "word": "bearbeiten", "en_meaning": "to process" },
  { "word": "übersetzen", "en_meaning": "to translate" },
  { "word": "verfassen", "en_meaning": "to compose" },
  { "word": "behandeln", "en_meaning": "to treat" },
  { "word": "überarbeiten", "en_meaning": "to revise" },
  { "word": "aufbereiten", "en_meaning": "to prepare" },
  { "word": "zusammenfassen", "en_meaning": "to summarize" },
  { "word": "versichern", "en_meaning": "to insure" },
  { "word": "beachten", "en_meaning": "to observe" },
  { "word": "instruieren", "en_meaning": "to instruct" },
  { "word": "unterrichten", "en_meaning": "to teach" },
  { "word": "formulieren", "en_meaning": "to formulate" },
  { "word": "darstellen", "en_meaning": "to represent" },
  { "word": "kommunizieren", "en_meaning": "to communicate" },
  { "word": "verbinden", "en_meaning": "to link" },
  { "word": "ausdrücken", "en_meaning": "to express" },
  { "word": "verifizieren", "en_meaning": "to verify" },
  { "word": "ermitteln", "en_meaning": "to determine" },
  { "word": "optimieren", "en_meaning": "to optimize" },
  { "word": "verhandeln", "en_meaning": "to bargain" },
  { "word": "auslösen", "en_meaning": "to trigger" },
  { "word": "abstimmen", "en_meaning": "to coordinate" },
  { "word": "auffrischen", "en_meaning": "to refresh" },
  { "word": "abgeben", "en_meaning": "to submit" },
  { "word": "bewerten", "en_meaning": "to assess" },
  { "word": "nachverfolgen", "en_meaning": "to track" },
  { "word": "bewahren", "en_meaning": "to preserve" },
  { "word": "einsetzen", "en_meaning": "to deploy" },
  { "word": "vorbereiten", "en_meaning": "to prepare" },
  { "word": "realisieren", "en_meaning": "to realize" },
  { "word": "reagieren", "en_meaning": "to react" },
  { "word": "auswerten", "en_meaning": "to evaluate" },
  { "word": "beheben", "en_meaning": "to fix" },
  { "word": "ausnutzen", "en_meaning": "to exploit" },
  { "word": "abwickeln", "en_meaning": "to process" },
  { "word": "verzichten", "en_meaning": "to forgo" },
  { "word": "verlassen", "en_meaning": "to leave" },
  { "word": "erfüllen", "en_meaning": "to fulfill" },
  { "word": "anpassen", "en_meaning": "to adapt" },
  { "word": "umsetzen", "en_meaning": "to execute" }
]
